async_expo_push_notifications-2.3.1.dist-info/licenses/LICENSE
exponent_server_sdk/__init__.py
exponent_server_sdk/exceptions.py
exponent_server_sdk/http_client.py
exponent_server_sdk/models.py
async_expo_push_notifications-2.3.1.dist-info/METADATA
async_expo_push_notifications-2.3.1.dist-info/WHEEL
async_expo_push_notifications-2.3.1.dist-info/top_level.txt
async_expo_push_notifications-2.3.1.dist-info/RECORD
