Metadata-Version: 2.4
Name: async-expo-push-notifications
Version: 2.3.1
Summary: Expo Server SDK for Python with async/await support, Pydantic models, and full type hints
Author-email: Roach <tmdgusya@gmail.com>
Maintainer-email: Roach <tmdgusya@gmail.com>
License-Expression: MIT
Project-URL: Homepage, https://github.com/tmdgusya/async-expo-notification-sdk
Project-URL: Repository, https://github.com/tmdgusya/async-expo-notification-sdk
Project-URL: Issues, https://github.com/tmdgusya/async-expo-notification-sdk/issues
Project-URL: Documentation, https://github.com/tmdgusya/async-expo-notification-sdk#readme
Keywords: expo,push,notifications,async,pydantic,type-hints
Classifier: Development Status :: 5 - Production/Stable
Classifier: Intended Audience :: Developers
Classifier: Programming Language :: Python :: 3
Classifier: Programming Language :: Python :: 3.8
Classifier: Programming Language :: Python :: 3.9
Classifier: Programming Language :: Python :: 3.10
Classifier: Programming Language :: Python :: 3.11
Classifier: Programming Language :: Python :: 3.12
Classifier: Topic :: Software Development :: Libraries :: Python Modules
Classifier: Typing :: Typed
Requires-Python: >=3.8
License-File: LICENSE
Requires-Dist: requests>=2.25.0
Requires-Dist: httpx>=0.24.0
Requires-Dist: pydantic>=2.0.0
Provides-Extra: dev
Requires-Dist: pytest>=7.0.0; extra == "dev"
Requires-Dist: pytest-asyncio>=0.21.0; extra == "dev"
Requires-Dist: pytest-cov>=4.0.0; extra == "dev"
Dynamic: license-file
